LICENSE
MANIFEST.in
README.md
setup.cfg
setup.py
multistack/__init__.py
multistack/client.py
multistack/config.py
multistack/credentials.py
multistack/shell.py
multistack/utils.py
multistack.egg-info/PKG-INFO
multistack.egg-info/SOURCES.txt
multistack.egg-info/dependency_links.txt
multistack.egg-info/entry_points.txt
multistack.egg-info/requires.txt
multistack.egg-info/top_level.txt
multistack/clients/__init__.py
multistack/clients/ceilometer.py
multistack/clients/cinder.py
multistack/clients/glance.py
multistack/clients/heat.py
multistack/clients/keystone.py
multistack/clients/neutron.py
multistack/clients/nova.py
multistack/clients/openstack.py
multistack/clients/solum.py
multistack/clients/swift.py
multistack/clients/trove.py