Metadata-Version: 1.1
Name: multistack
Version: 0.4.1
Summary: Universal wrapper for the various OpenStack client software with support for multiple environments.
Home-page: https://github.com/testeddoughnut/multistack
Author: M. David Bennett
Author-email: mdavidbennett@syntheticworks.com
License: Apache License, Version 2.0
Download-URL: https://github.com/testeddoughnut/multistack/releases/latest
Platform: UNKNOWN
Classifier: Development Status :: 5 - Production/Stable
Classifier: Environment :: Console
Classifier: Intended Audience :: Developers
Classifier: Intended Audience :: Information Technology
Classifier: License :: OSI Approved :: Apache Software License
Classifier: Operating System :: OS Independent
Classifier: Environment :: OpenStack
Classifier: Programming Language :: Python
